{"cameraMode":{"drawMode":0,"name":"Shaded","section":"Shading Mode"},"sceneLighting":true,"audioPlay":false,"sceneViewState":{"showFog":false,"showMaterialUpdate":false,"showSkybox":false,"showFlares":false,"showImageEffects":true,"showParticleSystems":true,"showVisualEffectGraphs":true,"m_FxEnabled":true},"in2DMode":false,"pivot":{"x":5.020910263061523,"y":9.319375991821289,"z":-12.541525840759278},"rotation":{"x":-0.20100383460521699,"y":-0.35843926668167117,"z":0.07932979613542557,"w":-0.9082015156745911},"size":5.977156639099121,"orthographic":false}